README.txt
setup.cfg
setup.py
collective/__init__.py
collective.portlet.bilingualtext.egg-info/PKG-INFO
collective.portlet.bilingualtext.egg-info/SOURCES.txt
collective.portlet.bilingualtext.egg-info/dependency_links.txt
collective.portlet.bilingualtext.egg-info/entry_points.txt
collective.portlet.bilingualtext.egg-info/namespace_packages.txt
collective.portlet.bilingualtext.egg-info/not-zip-safe
collective.portlet.bilingualtext.egg-info/requires.txt
collective.portlet.bilingualtext.egg-info/top_level.txt
collective/portlet/__init__.py
collective/portlet/bilingualtext/__init__.py
collective/portlet/bilingualtext/bilingualtextportlet.pt
collective/portlet/bilingualtext/bilingualtextportlet.py
collective/portlet/bilingualtext/configure.zcml
collective/portlet/bilingualtext/version.txt
collective/portlet/bilingualtext/profiles/default/metadata.xml
collective/portlet/bilingualtext/profiles/default/portlets.xml
collective/portlet/bilingualtext/tests/__init__.py
collective/portlet/bilingualtext/tests/base.py
collective/portlet/bilingualtext/tests/test_portlet.py
docs/HISTORY.txt
docs/INSTALL.txt
docs/LICENSE.GPL
docs/LICENSE.txt