Metadata-Version: 1.0
Name: collective.portlet.bilingualtext
Version: 0.1.0
Summary: A bi-lingual text portlet for Plone 3
Home-page: http://plone.org
Author: Andreas Jung
Author-email: info@zopyx.com
License: ZPL
Keywords: Plone Portlet Text
Platform: UNKNOWN
Classifier: Framework :: Plone
Classifier: Programming Language :: Python
Classifier: Topic :: Software Development :: Libraries :: Python Modules
